[
	{
		"name": "Mitko",
		"username": "MitkoYT",
		"image": "/img/mitko.jpg",
		"buttons": [
			{
				"label": "GitHub",
				"href": "https://github.com/usarana"
			},
			{
				"label": "Telegram",
				"href": "https://t.me/MitkoYT"
			}
		]
	},
	{
		"name": "Tizu",
		"username": "tizu69",
		"image": "/img/tizu.jpg",
		"buttons": [
			{
				"label": "GitHub",
				"href": "https://github.com/tizu69"
			}
		]
	},
	{
		"name": "Bumblebee",
		"username": "Bumblebee437",
		"image": "/img/bumblebee.jpg",
		"buttons": [
			{
				"label": "GitHub",
				"href": "https://github.com/bumbelbee777"
			},
			{
				"label": "Telegram",
				"href": "https://t.me/Bumblebee437"
			}
		]
	},
	{
		"name": "Boro",
		"username": "BoroMoro",
		"image": "/img/boro.jpg",
		"buttons": [
			{
				"label": "Telegram",
				"href": "https://t.me/BoroMoro"
			},
			{
				"label": "Discord",
				"href": "https://discord.com/users/371351698813353994"
			}
		]
	},
	{
		"name": "kris",
		"username": "kristiannotfound",
		"image": "/img/kris.jpg",
		"buttons": [
			{
				"label": "GitHub",
				"href": "https://github.com/kristianthekot"
			},
			{
				"label": "Telegram",
				"href": "https://t.me/kristiannotfound"
			}
		]
	},
	{
		"name": "Java",
		"username": "javtheslav",
		"image": "/img/java.jpg",
		"buttons": [
			{
				"label": "GitHub",
				"href": "https://github.com/javtheslav"
			},
			{
				"label": "Telegram",
				"href": "https://t.me/javtheslav"
			}
		]
	},
	{
		"name": "dripbert",
		"username": "dripbert",
		"image": "/img/dripbert.jpg",
		"buttons": [
			{
				"label": "GitHub",
				"href": "https://github.com/dripbert"
			},
			{
				"label": "Telegram",
				"href": "https://t.me/dripbert"
			}
		]
	},
	{
		"name": "Phenrir",
		"username": "itsphenrir",
		"image": "/img/phenrir.jpg",
		"buttons": [
			{
				"label": "Discord",
				"href": "https://discord.com/users/836877858496184320"
			},
			{
				"label": "Twitter",
				"href": "https://twitter.com/ItsPhenrir"
			}
		]
	}
]
